{
  "headers": {
    "server": "nginx/1.6.2",
    "date": "Sat, 21 Dec 2024 17:16:17 GMT",
    "content-type": "application/javascript; charset=UTF-8",
    "transfer-encoding": "chunked",
    "connection": "keep-alive",
    "x-powered-by": "PHP/7.3.31-1~deb10u1",
    "expires": "Sun, 21 Dec 2025 17:16:17 GMT",
    "cache-control": "public, max-age=31536000",
    "x-ua-compatible": "IE=edge",
    "x-content-type-options": "nosniff"
  },
  "status": 200,
  "uri": "https://www.libregraphicsmeeting.org/lgm/wp/wp-admin/load-scripts.php?c=0&load%5Bchunk_0%5D=clipboard"
}